pyponto/__init__.py
pyponto/settings.py
pyponto/urls.py
pyponto/wsgi.py
pyponto-1.0.0.dist-info/LICENSE
pyponto-1.0.0.dist-info/METADATA
pyponto-1.0.0.dist-info/WHEEL
pyponto-1.0.0.dist-info/top_level.txt
pyponto-1.0.0.dist-info/RECORD
