Metadata-Version: 2.1
Name: pyponto
Version: 1.0.0
Summary: Registrar ponto de funcionários
Home-page: https://github.com/hendrixcosta/pyponto
Author: Hendrix Costa
Author-email: hendrixcosta@gmail.com
License: MIT License
Keywords: pyponto registro ponto funcionario
Platform: UNKNOWN
Classifier: Development Status :: 5 - Production/Stable
Classifier: Intended Audience :: Developers
Classifier: Natural Language :: Portuguese
Classifier: License :: OSI Approved :: MIT License
Classifier: Programming Language :: Python :: 3.5
Classifier: Programming Language :: Python :: 3.6
